aiofluent/__init__.py
aiofluent/glogging.py
aiofluent_python-0.3.0.dist-info/LICENSE
aiofluent_python-0.3.0.dist-info/METADATA
aiofluent_python-0.3.0.dist-info/WHEEL
aiofluent_python-0.3.0.dist-info/top_level.txt
aiofluent_python-0.3.0.dist-info/RECORD
