Metadata-Version: 2.1
Name: aiofluent-python
Version: 0.3.0
Summary: asynchronous fluentd client libary
Home-page: https://github.com/guyingbo/aiofluent
Author: Yingbo Gu
Author-email: tensiongyb@gmail.com
Maintainer: Yingbo Gu
Maintainer-email: tensiongyb@gmail.com
License: MIT
Platform: UNKNOWN
Classifier: License :: OSI Approved :: MIT License
Classifier: Programming Language :: Python
Classifier: Programming Language :: Python :: 3
Classifier: Programming Language :: Python :: 3.5
Classifier: Programming Language :: Python :: 3.6
Classifier: Programming Language :: Python :: 3.7
Classifier: Programming Language :: Python :: 3.8
Classifier: Intended Audience :: Developers
Requires-Python: >=3.5.3
Requires-Dist: msgpack (>=0.5.2)
Requires-Dist: async-timeout (>=2.0.0)
